fremu/__ini__.py
fremu/fremu.py
fremu/cache/k.npy
fremu/cache/pc_0.0.npy
fremu/cache/pc_0.5.npy
fremu/cache/pc_1.0.npy
fremu/cache/pc_2.0.npy
fremu/cache/pc_3.0.npy
fremu/cache/pc_ann_0.0.pth
fremu/cache/pc_ann_0.5.pth
fremu/cache/pc_ann_1.0.pth
fremu/cache/pc_ann_2.0.pth
fremu/cache/pc_ann_3.0.pth
fremu/cache/scaler.pkl
fremu/cache/sigma.npy
fremu-0.0.9.dist-info/METADATA
fremu-0.0.9.dist-info/WHEEL
fremu-0.0.9.dist-info/top_level.txt
fremu-0.0.9.dist-info/RECORD
