Metadata-Version: 2.1
Name: fremu
Version: 0.0.9
Summary: Emulator for f(R) gravity
Home-page: https://github.com/astrobai/fremu
Author: Jiachen Bai
Author-email: astrobaijc@gmail.com
License: UNKNOWN
Platform: UNKNOWN
Classifier: Programming Language :: Python :: 3
Classifier: License :: OSI Approved :: MIT License
Classifier: Operating System :: OS Independent
Requires-Dist: camb
Requires-Dist: numpy
Requires-Dist: scikit-learn
Requires-Dist: scipy
Requires-Dist: torch
